gen_arm32asm/__init__.py
gen_arm32asm/py.typed
gen_arm32asm/conf/gen_arm32asm.cfg
gen_arm32asm/conf/gen_arm32asm.logo
gen_arm32asm/conf/gen_arm32asm_util.cfg
gen_arm32asm/conf/project.yaml
gen_arm32asm/conf/template/asmflags.template
gen_arm32asm/conf/template/ldflags.template
gen_arm32asm/conf/template/main.template
gen_arm32asm/conf/template/objects.template
gen_arm32asm/conf/template/sources.template
gen_arm32asm/pro/__init__.py
gen_arm32asm/pro/read_template.py
gen_arm32asm/pro/write_template.py
usr/local/bin/gen_arm32asm_run.py
gen_arm32asm-1.0.2.dist-info/LICENSE
gen_arm32asm-1.0.2.dist-info/METADATA
gen_arm32asm-1.0.2.dist-info/WHEEL
gen_arm32asm-1.0.2.dist-info/top_level.txt
gen_arm32asm-1.0.2.dist-info/RECORD
