Metadata-Version: 2.2
Name: gen_arm32asm
Version: 1.0.2
Summary: Generating ARM 32-bit asm project
Home-page: https://vroncevic.github.io/gen_arm32asm
Author: Vladimir Roncevic
Author-email: elektron.ronca@gmail.com
License: GPL-3.0-or-later
Keywords: Unix,Linux,Development,assembly,ARM32,generator
Platform: POSIX
Classifier: Programming Language :: Python :: 3.10
Classifier: Programming Language :: Python :: 3.11
Classifier: License :: OSI Approved :: GNU Lesser General Public License v2 (LGPLv2)
Classifier: License :: OSI Approved :: GNU Lesser General Public License v2 or later (LGPLv2+)
Classifier: License :: OSI Approved :: GNU Lesser General Public License v3 (LGPLv3)
Classifier: License :: OSI Approved :: GNU Lesser General Public License v3 or later (LGPLv3+)
Classifier: License :: OSI Approved :: GNU Library or Lesser General Public License (LGPL)
License-File: LICENSE
Requires-Dist: ats-utilities
Provides-Extra: dev
Requires-Dist: pytest; extra == "dev"
Requires-Dist: mypy; extra == "dev"
Requires-Dist: flake8; extra == "dev"
Dynamic: author
Dynamic: author-email
Dynamic: classifier
Dynamic: description
Dynamic: description-content-type
Dynamic: home-page
Dynamic: keywords
Dynamic: license
Dynamic: platform
Dynamic: provides-extra
Dynamic: requires-dist
Dynamic: summary
